steamdeck_hid/__init__.py
steamdeck_hid/main.py
steamdeck_hid/test.py
steamdeck_hid-0.2.7.dist-info/METADATA
steamdeck_hid-0.2.7.dist-info/WHEEL
steamdeck_hid-0.2.7.dist-info/licenses/LICENSE
steamdeck_hid-0.2.7.dist-info/RECORD
