Metadata-Version: 2.4
Name: steamdeck-hid
Version: 0.2.7
Summary: A Python library for handling Steam Deck inputs
Project-URL: Homepage, https://github.com/ollleg/steamdeck-hid
Project-URL: Source, https://github.com/ollleg/steamdeck-hid
Project-URL: Issues, https://github.com/ollleg/steamdeck-hid/issues
Author-email: Oleh Polishchuk <olllejik@gmail.com>
License: MIT License
License-File: LICENSE
Classifier: License :: OSI Approved :: MIT License
Classifier: Operating System :: POSIX :: Linux
Classifier: Programming Language :: Python :: 3
Requires-Python: >=3.8
Requires-Dist: evdev>=1.9.2; sys_platform == 'linux'
Requires-Dist: hid>=1.0.8
